kagimcp/__init__.py
kagimcp/server.py
kagimcp-0.1.3.dist-info/METADATA
kagimcp-0.1.3.dist-info/WHEEL
kagimcp-0.1.3.dist-info/entry_points.txt
kagimcp-0.1.3.dist-info/licenses/LICENSE
kagimcp-0.1.3.dist-info/RECORD
