Metadata-Version: 2.4
Name: kagimcp
Version: 0.1.3
Summary: Kagi MCP server
Project-URL: Homepage, https://github.com/kagisearch/kagi-mcp
Project-URL: Issues, https://github.com/kagisearch/kagi-mcp/issues
Author-email: Rehan Ali Rana <rehan@kagi.com>
License-File: LICENSE
Requires-Python: >=3.12
Requires-Dist: kagiapi~=0.2.1
Requires-Dist: mcp[cli]~=1.6.0
Requires-Dist: pydantic~=2.10.3
